conn2combat/__init__.py
conn2combat/firstlevelparser.py
conn2combat-1.0.0.dist-info/METADATA
conn2combat-1.0.0.dist-info/WHEEL
conn2combat-1.0.0.dist-info/entry_points.txt
conn2combat-1.0.0.dist-info/top_level.txt
conn2combat-1.0.0.dist-info/RECORD
