Metadata-Version: 2.1
Name: conn2combat
Version: 1.0.0
Summary: A package for parsing .mat files from CONN first-level ROI-to-ROI analyses and preparing data for COMBAT.
Home-page: https://github.com/trevorbryanjackson/conn2combat
Author: T. Bryan Jackson
Author-email: trevorbryanjackson@gmail.com
Classifier: Programming Language :: Python :: 3
Classifier: License :: OSI Approved :: MIT License
Classifier: Operating System :: OS Independent
Requires-Python: >=3.6
Requires-Dist: h5py==3.12.1
Requires-Dist: pandas==2.2.3
